ElasticsearchJavaShouce/README.md
ElasticsearchJavaShouce/__init__.py
ElasticsearchJavaShouce/__main__.py
ElasticsearchJavaShouce/file.epub
ElasticsearchJavaShouce/index.html
ElasticsearchJavaShouce/css/__init__.py
ElasticsearchJavaShouce/css/annotations.css
ElasticsearchJavaShouce/css/main.css
ElasticsearchJavaShouce/css/normalize.css
ElasticsearchJavaShouce/css/popup.css
ElasticsearchJavaShouce/font/__init__.py
ElasticsearchJavaShouce/font/fontello.eot
ElasticsearchJavaShouce/font/fontello.svg
ElasticsearchJavaShouce/font/fontello.ttf
ElasticsearchJavaShouce/font/fontello.woff
ElasticsearchJavaShouce/img/__init__.py
ElasticsearchJavaShouce/img/annotator-glyph-sprite.png
ElasticsearchJavaShouce/img/annotator-icon-sprite.png
ElasticsearchJavaShouce/img/apple-touch-icon.png
ElasticsearchJavaShouce/img/cancelfullscreen.png
ElasticsearchJavaShouce/img/close.png
ElasticsearchJavaShouce/img/fullscreen.png
ElasticsearchJavaShouce/img/loader.gif
ElasticsearchJavaShouce/img/menu-icon.png
ElasticsearchJavaShouce/img/save.png
ElasticsearchJavaShouce/img/saved.png
ElasticsearchJavaShouce/img/settings-s.png
ElasticsearchJavaShouce/img/settings.png
ElasticsearchJavaShouce/img/star.png
ElasticsearchJavaShouce/js/__init__.py
ElasticsearchJavaShouce/js/epub.js
ElasticsearchJavaShouce/js/epub.min.js
ElasticsearchJavaShouce/js/epub.min.map
ElasticsearchJavaShouce/js/hooks.min.js
ElasticsearchJavaShouce/js/hooks.min.map
ElasticsearchJavaShouce/js/reader.js
ElasticsearchJavaShouce/js/reader.js.map
ElasticsearchJavaShouce/js/reader.min.js
ElasticsearchJavaShouce/js/reader.min.map
ElasticsearchJavaShouce/js/hooks/__init__.py
ElasticsearchJavaShouce/js/hooks/extensions/__init__.py
ElasticsearchJavaShouce/js/hooks/extensions/highlight.js
ElasticsearchJavaShouce/js/libs/__init__.py
ElasticsearchJavaShouce/js/libs/jquery.min.js
ElasticsearchJavaShouce/js/libs/localforage.min.js
ElasticsearchJavaShouce/js/libs/screenfull.js
ElasticsearchJavaShouce/js/libs/screenfull.min.js
elasticsearch_java_shouce-2024.3.2.0.dist-info/METADATA
elasticsearch_java_shouce-2024.3.2.0.dist-info/WHEEL
elasticsearch_java_shouce-2024.3.2.0.dist-info/entry_points.txt
elasticsearch_java_shouce-2024.3.2.0.dist-info/top_level.txt
elasticsearch_java_shouce-2024.3.2.0.dist-info/RECORD
